README.md
setup.py
blockstack_proofs/__init__.py
blockstack_proofs/config.py
blockstack_proofs/domain.py
blockstack_proofs/htmlparsing.py
blockstack_proofs/proofs.py
blockstack_proofs/sites.py
blockstack_proofs.egg-info/PKG-INFO
blockstack_proofs.egg-info/SOURCES.txt
blockstack_proofs.egg-info/dependency_links.txt
blockstack_proofs.egg-info/not-zip-safe
blockstack_proofs.egg-info/requires.txt
blockstack_proofs.egg-info/top_level.txt