Metadata-Version: 1.1
Name: blockstack-proofs
Version: 0.0.9
Summary: Python library for verifying proofs (twitter, github, domains etc) linked to a blockchain ID
Home-page: https://github.com/blockstack/blockstack-proofs
Author: Blockstack.org
Author-email: support@blockstack.org
License: MIT
Download-URL: https://github.com/blockstack/blockstack-proofs/archive/master.zip
Keywords: blockchain bitcoin social proof verifications identity
Platform: UNKNOWN
Classifier: Intended Audience :: Developers
Classifier: License :: OSI Approved :: MIT License
Classifier: Operating System :: OS Independent
Classifier: Programming Language :: Python
Classifier: Topic :: Internet
Classifier: Topic :: Security :: Cryptography
Classifier: Topic :: Software Development :: Libraries :: Python Modules
